NaaVRE_containerizer_jupyterlab/__init__.py
NaaVRE_containerizer_jupyterlab/_version.py
naavre_containerizer_jupyterlab-0.4.3.data/data/share/jupyter/labextensions/@naavre/containerizer-jupyterlab/package.json
naavre_containerizer_jupyterlab-0.4.3.data/data/share/jupyter/labextensions/@naavre/containerizer-jupyterlab/schemas/@naavre/containerizer-jupyterlab/package.json.orig
naavre_containerizer_jupyterlab-0.4.3.data/data/share/jupyter/labextensions/@naavre/containerizer-jupyterlab/schemas/@naavre/containerizer-jupyterlab/plugin.json
naavre_containerizer_jupyterlab-0.4.3.data/data/share/jupyter/labextensions/@naavre/containerizer-jupyterlab/static/160.a5e1444a826c0bd83b33.js
naavre_containerizer_jupyterlab-0.4.3.data/data/share/jupyter/labextensions/@naavre/containerizer-jupyterlab/static/162.f5bb167bf55c50be96b4.js
naavre_containerizer_jupyterlab-0.4.3.data/data/share/jupyter/labextensions/@naavre/containerizer-jupyterlab/static/208.f45cf5f5b93245be6652.js
naavre_containerizer_jupyterlab-0.4.3.data/data/share/jupyter/labextensions/@naavre/containerizer-jupyterlab/static/215.daef74cd5d197a1ce25c.js
naavre_containerizer_jupyterlab-0.4.3.data/data/share/jupyter/labextensions/@naavre/containerizer-jupyterlab/static/215.daef74cd5d197a1ce25c.js.LICENSE.txt
naavre_containerizer_jupyterlab-0.4.3.data/data/share/jupyter/labextensions/@naavre/containerizer-jupyterlab/static/291.b89e6d2c106ba60e119b.js
naavre_containerizer_jupyterlab-0.4.3.data/data/share/jupyter/labextensions/@naavre/containerizer-jupyterlab/static/328.8872be7c94e742825d67.js
naavre_containerizer_jupyterlab-0.4.3.data/data/share/jupyter/labextensions/@naavre/containerizer-jupyterlab/static/328.8872be7c94e742825d67.js.LICENSE.txt
naavre_containerizer_jupyterlab-0.4.3.data/data/share/jupyter/labextensions/@naavre/containerizer-jupyterlab/static/487.7debb540dd4c715189f0.js
naavre_containerizer_jupyterlab-0.4.3.dist-info/METADATA
naavre_containerizer_jupyterlab-0.4.3.dist-info/WHEEL
naavre_containerizer_jupyterlab-0.4.3.dist-info/licenses/LICENSE
naavre_containerizer_jupyterlab-0.4.3.dist-info/RECORD
