Metadata-Version: 2.4
Name: NaaVRE_containerizer_jupyterlab
Version: 0.4.3
Summary: NaaVRE cells containerizer frontend on Jupyter Lab
Project-URL: Homepage, https://github.com/NaaVRE/NaaVRE-containerizer-jupyterlab
Project-URL: Bug Tracker, https://github.com/NaaVRE/NaaVRE-containerizer-jupyterlab/issues
Project-URL: Repository, https://github.com/NaaVRE/NaaVRE-containerizer-jupyterlab.git
Author-email: LifeWatch ERIC VLIC & QCDIS team at University of Amsterdam <gabriel.pelouze@lifewatch.eu>
License: 
License-File: LICENSE
Keywords: jupyter,jupyterlab,jupyterlab-extension
Classifier: Framework :: Jupyter
Classifier: Framework :: Jupyter :: JupyterLab
Classifier: Framework :: Jupyter :: JupyterLab :: 4
Classifier: Framework :: Jupyter :: JupyterLab :: Extensions
Classifier: Framework :: Jupyter :: JupyterLab :: Extensions :: Prebuilt
Classifier: License :: OSI Approved :: Apache Software License
Classifier: Programming Language :: Python
Classifier: Programming Language :: Python :: 3
Classifier: Programming Language :: Python :: 3.8
Classifier: Programming Language :: Python :: 3.9
Classifier: Programming Language :: Python :: 3.10
Classifier: Programming Language :: Python :: 3.11
Classifier: Programming Language :: Python :: 3.12
Requires-Python: >=3.8
Requires-Dist: naavre-communicator-jupyterlab>=0.3.0
